sdsort/__init__.py
sdsort-0.1.1.dist-info/entry_points.txt
sdsort-0.1.1.dist-info/WHEEL
sdsort-0.1.1.dist-info/METADATA
sdsort-0.1.1.dist-info/RECORD
