Metadata-Version: 2.1
Name: sdsort
Version: 0.1.1
Summary: Sorts class methods according to the step-down rule
Home-page: https://github.com/eirikurt/sdsort
Author: Eiríkur Fannar Torfason
Author-email: eirikur.torfason@gmail.com
Requires-Python: >=3.7,<4.0
Classifier: Programming Language :: Python :: 3
Classifier: Programming Language :: Python :: 3.7
Classifier: Programming Language :: Python :: 3.8
Classifier: Programming Language :: Python :: 3.9
Requires-Dist: click (>=7.1.2,<8.0.0)
Project-URL: Repository, https://github.com/eirikurt/sdsort
